dockerclean/__init__.py
dockerclean/cleaner.py
dockerclean/cli.py
docker_cleanup-1.0.0.dist-info/METADATA
docker_cleanup-1.0.0.dist-info/WHEEL
docker_cleanup-1.0.0.dist-info/entry_points.txt
docker_cleanup-1.0.0.dist-info/licenses/LICENSE
docker_cleanup-1.0.0.dist-info/RECORD
