Metadata-Version: 2.4
Name: docker-cleanup
Version: 1.0.0
Summary: A CLI tool to clean all Docker resources quickly
Project-URL: Homepage, https://github.com/developer0hye/docker-cleanup
Author-email: Yonghye Kwon <developer.0hye@gmail.com>
License-File: LICENSE
Classifier: License :: OSI Approved :: MIT License
Classifier: Operating System :: OS Independent
Classifier: Programming Language :: Python :: 3
Requires-Python: >=3.7
